inclusive_code.py
inclusive_code-0.1.1.dist-info/WHEEL
inclusive_code-0.1.1.dist-info/METADATA
inclusive_code-0.1.1.dist-info/RECORD
