Metadata-Version: 2.1
Name: inclusive-code
Version: 0.1.1
Summary: A custom Pylint checker to enforce an inclusive language style guide
License: MIT
Author: Helen Stockman
Author-email: helen@flexport.com
Requires-Python: >=3.6,<4.0
Classifier: License :: OSI Approved :: MIT License
Classifier: Programming Language :: Python :: 3
Classifier: Programming Language :: Python :: 3.6
Classifier: Programming Language :: Python :: 3.7
Classifier: Programming Language :: Python :: 3.8
Classifier: Programming Language :: Python :: 3.9
Requires-Dist: PyYAML (>=5.4.1,<6.0.0)
Requires-Dist: pyhumps (>=1.6.1,<2.0.0)
Requires-Dist: pylint (>=2.8.2,<3.0.0)
